project_foundry/__init__.py
project_foundry/_version.py
project_foundry/cli/__init__.py
project_foundry/cli/main.py
project_foundry-0.2.0.dist-info/entry_points.txt
project_foundry-0.2.0.dist-info/WHEEL
project_foundry-0.2.0.dist-info/METADATA
project_foundry-0.2.0.dist-info/license_files/LICENSES/MIT.txt
project_foundry-0.2.0.dist-info/license_files/LICENSES/CC0-1.0.txt
project_foundry-0.2.0.dist-info/license_files/LICENSES/CC-BY-SA-4.0.txt
project_foundry-0.2.0.dist-info/RECORD
