Metadata-Version: 2.1
Name: project-foundry
Version: 0.2.0
Summary: A tool for casting projects from molds.
License: MIT AND CC0-1.0 AND CC-BY-SA-4.0
Keywords: command line tool,templating,project templating
Author-email: crai0 <crai0@posteo.net>
Requires-Python: ~=3.10
Classifier: Development Status :: 1 - Planning
Classifier: Environment :: Console
Classifier: Intended Audience :: Developers
Classifier: Intended Audience :: Information Technology
Classifier: License :: CC0 1.0 Universal (CC0 1.0) Public Domain Dedication
Classifier: License :: OSI Approved :: MIT License
Classifier: Natural Language :: English
Classifier: Operating System :: OS Independent
Classifier: Programming Language :: Python
Classifier: Programming Language :: Python :: 3 :: Only
Classifier: Programming Language :: Python :: 3.10
Classifier: Topic :: Software Development
Classifier: Topic :: Utilities
Classifier: Typing :: Typed
Requires-Dist: click~=8.1
Project-URL: Changelog, https://crai0.gitlab.io/project-foundry/changelog.html
Project-URL: Homepage, https://crai0.gitlab.io/project-foundry
Project-URL: Source, https://gitlab.com/crai0/project-foundry
Project-URL: Tracker, https://gitlab.com/crai0/project-foundry/-/issues
